<?xml version="1.0" encoding="UTF-8"?>
<configuration>

    <!-- Texto simples para desenvolvimento -->
    <springProfile name="!prod">
        <include resource="org/springframework/boot/logging/logback/defaults.xml"/>
        <include resource="org/springframework/boot/logging/logback/console-appender.xml"/>
        <root level="INFO">
            <appender-ref ref="CONSOLE"/>
        </root>
    </springProfile>

    <!-- JSON estruturado para produção (ingestão no ELK / Loki) -->
    <springProfile name="prod">
        <appender name="JSON_CONSOLE" class="ch.qos.logback.core.ConsoleAppender">
            <encoder class="net.logstash.logback.encoder.LogstashEncoder">
                <includeCallerData>false</includeCallerData>
                <fieldNames>
                    <timestamp>timestamp</timestamp>
                    <message>message</message>
                    <logger>logger</logger>
                    <thread>thread</thread>
                    <level>level</level>
                    <levelValue>[ignore]</levelValue>
                    <version>[ignore]</version>
                </fieldNames>
            </encoder>
        </appender>
        <root level="INFO">
            <appender-ref ref="JSON_CONSOLE"/>
        </root>
    </springProfile>

</configuration>
